pygitops/__init__.py
pygitops/_constants.py
pygitops/_util.py
pygitops/exceptions.py
pygitops/operations.py
pygitops/remote_git_utils.py
pygitops/types.py
pygitops-0.17.0.dist-info/METADATA
pygitops-0.17.0.dist-info/WHEEL
pygitops-0.17.0.dist-info/licenses/LICENSE
pygitops-0.17.0.dist-info/RECORD
