Metadata-Version: 2.1
Name: pygitops
Version: 0.17.0
Summary: Wrapper for low-level git logic. Useful for systems automating git operations.
Project-URL: Homepage, https://github.com/wayfair-incubator/pygitops
Project-URL: changelog, https://github.com/wayfair-incubator/pygitops/blob/main/CHANGELOG.md
Project-URL: issues, https://github.com/wayfair-incubator/pygitops/issues
Project-URL: documentation, https://wayfair-incubator.github.io/pygitops
Author-email: Josh Woodward <josh.woodward2693@gmail.com>
License: MIT
License-File: LICENSE
Classifier: Development Status :: 4 - Beta
Classifier: License :: OSI Approved :: MIT License
Classifier: Programming Language :: Python
Classifier: Programming Language :: Python :: 3
Classifier: Programming Language :: Python :: 3.10
Classifier: Programming Language :: Python :: 3.11
Classifier: Programming Language :: Python :: 3.12
Classifier: Programming Language :: Python :: 3.13
Classifier: Programming Language :: Python :: 3.14
Requires-Python: >=3.10
Requires-Dist: filelock<4,>=3.4
Requires-Dist: gitpython<4,>=3.1
